[{"x": 0.332, "y": 227.87}, {"x": 0.382, "y": 259.21}, {"x": 0.574, "y": 217.06}, {"x": 0.624, "y": 197.2}, {"x": 0.674, "y": 188.86}, {"x": 0.724, "y": 188.0}, {"x": 0.774, "y": 185.93}, {"x": 0.976, "y": 99.87}, {"x": 1.026, "y": 102.3}, {"x": 1.076, "y": 105.85}, {"x": 1.126, "y": 115.38}, {"x": 1.242, "y": 271.57}, {"x": 1.292, "y": 280.57}, {"x": 1.342, "y": 276.93}, {"x": 1.528, "y": 101.79}, {"x": 1.578, "y": 102.51}, {"x": 1.628, "y": 103.22}, {"x": 1.77, "y": 200.29}, {"x": 1.82, "y": 189.7}, {"x": 1.871, "y": 94.75}, {"x": 1.921, "y": 98.91}, {"x": 2.143, "y": 183.73}, {"x": 2.193, "y": 178.37}, {"x": 2.482, "y": 99.75}]
